auroraviz/charts.py
auroraviz/init.py
auroraviz/palettes.py
auroraviz/theme.py
auroraviz/utils.py
auroraviz/styles/aurora-dark.mplstyle
auroraviz/styles/aurora.mplstyle
auroraviz-0.1.3.dist-info/licenses/LICENSE
auroraviz-0.1.3.dist-info/METADATA
auroraviz-0.1.3.dist-info/WHEEL
auroraviz-0.1.3.dist-info/top_level.txt
auroraviz-0.1.3.dist-info/RECORD
