Metadata-Version: 2.4
Name: auroraviz
Version: 0.1.3
Summary: A clean, modern Python visualization library with curated palettes and minimal ink.
Author: Gyanankur Baruah
License: MIT License
Keywords: visualization,charts,matplotlib,data viz,design
Classifier: Programming Language :: Python :: 3
Classifier: License :: OSI Approved :: MIT License
Classifier: Intended Audience :: Developers
Classifier: Topic :: Scientific/Engineering :: Visualization
Requires-Python: >=3.9
License-File: LICENSE
Requires-Dist: matplotlib>=3.7
Requires-Dist: numpy>=1.24
Requires-Dist: pandas>=2.0
Dynamic: license-file
